robothon/__init__.py
robothon/config.py
robothon/executionbot.py
robothon/simplebot.py
sample/__init__.py
sample/package_data.dat
sample/simple.py
robothon2021-1.1.6.dist-info/LICENSE.txt
robothon2021-1.1.6.dist-info/METADATA
robothon2021-1.1.6.dist-info/WHEEL
robothon2021-1.1.6.dist-info/entry_points.txt
robothon2021-1.1.6.dist-info/top_level.txt
robothon2021-1.1.6.dist-info/RECORD
